Metadata-Version: 1.0
Name: afdd-distributions
Version: 0.1
Summary: Gaussian and Binomial distributions
Home-page: UNKNOWN
Author: Andres Dorado
Author-email: andres.dorado90@gmail.com
License: UNKNOWN
Platform: UNKNOWN
